[1,["fanJddG51IqKKUvxmo+eEL"],["_texture"],[["dragonBones.DragonBonesAtlasAsset",["_name","_atlasJson"],1]],[[0,0,1,3]],[[0,"moto_tex","{\"imagePath\":\"moto_tex.png\",\"name\":\"moto_tex\",\"SubTexture\":[{\"width\":40,\"y\":185,\"height\":40,\"name\":\"摩托/轮子2\",\"x\":78},{\"width\":40,\"y\":201,\"height\":40,\"name\":\"摩托/轮子3\",\"x\":1},{\"width\":14,\"y\":245,\"height\":18,\"name\":\"摩托/避震\",\"x\":95},{\"frameX\":0,\"y\":37,\"frameY\":-5,\"frameWidth\":101,\"width\":101,\"frameHeight\":57,\"height\":51,\"name\":\"摩托/摩托车身\",\"x\":88},{\"width\":17,\"y\":81,\"height\":7,\"name\":\"摩托/机枪2\",\"x\":191},{\"width\":19,\"y\":171,\"height\":11,\"name\":\"摩托/机枪1\",\"x\":236},{\"width\":13,\"y\":225,\"height\":23,\"name\":\"摩托/机枪架子\",\"x\":146},{\"width\":66,\"y\":90,\"height\":55,\"name\":\"摩托/架子\",\"x\":88},{\"width\":86,\"y\":90,\"height\":32,\"name\":\"摩托/车斗\",\"x\":156},{\"width\":40,\"y\":39,\"height\":40,\"name\":\"摩托/轮1\",\"x\":191},{\"width\":52,\"y\":222,\"height\":28,\"name\":\"摩托/宽体\",\"x\":164},{\"width\":22,\"y\":227,\"height\":16,\"name\":\"摩托/车把\",\"x\":95},{\"width\":85,\"y\":37,\"height\":68,\"name\":\"枪花/图层_97_拷贝\",\"x\":1},{\"width\":43,\"y\":185,\"height\":35,\"name\":\"枪花/图层_97_拷贝_2\",\"x\":164},{\"width\":181,\"y\":1,\"height\":34,\"name\":\"枪花/图层_97\",\"x\":1},{\"width\":9,\"y\":18,\"height\":14,\"name\":\"1/rl\",\"x\":244},{\"width\":10,\"y\":1,\"height\":15,\"name\":\"1/ll\",\"x\":244},{\"frameX\":0,\"y\":89,\"frameY\":0,\"frameWidth\":11,\"width\":11,\"frameHeight\":15,\"height\":15,\"name\":\"1/rl2\",\"x\":244},{\"width\":12,\"y\":250,\"height\":16,\"name\":\"1/ll2\",\"x\":78},{\"width\":20,\"y\":227,\"height\":21,\"name\":\"1/body\",\"x\":73},{\"width\":24,\"y\":225,\"height\":19,\"name\":\"1/fangdanyi\",\"x\":120},{\"width\":18,\"y\":151,\"height\":18,\"name\":\"1/rh\",\"x\":236},{\"width\":13,\"y\":246,\"height\":12,\"name\":\"1/yixiu2\",\"x\":111},{\"frameX\":0,\"y\":124,\"frameY\":0,\"frameWidth\":15,\"width\":15,\"frameHeight\":25,\"height\":25,\"name\":\"1/lh\",\"x\":236},{\"width\":15,\"y\":252,\"height\":16,\"name\":\"1/衣袖\",\"x\":61},{\"frameX\":-3,\"y\":185,\"frameY\":0,\"frameWidth\":46,\"width\":42,\"frameHeight\":38,\"height\":38,\"name\":\"1/head\",\"x\":120},{\"frameX\":-1,\"y\":229,\"frameY\":-2,\"frameWidth\":26,\"width\":26,\"frameHeight\":16,\"height\":14,\"name\":\"1/eye3\",\"x\":43},{\"frameX\":-18,\"y\":258,\"frameY\":-18,\"frameWidth\":46,\"width\":24,\"frameHeight\":38,\"height\":9,\"name\":\"1/eye\",\"x\":29},{\"width\":30,\"y\":245,\"height\":11,\"name\":\"1/eye2\",\"x\":29},{\"frameX\":-10,\"y\":34,\"frameY\":-2,\"frameWidth\":24,\"width\":7,\"frameHeight\":6,\"height\":3,\"name\":\"1/mouth2\",\"x\":244},{\"width\":24,\"y\":259,\"height\":8,\"name\":\"1/mouth1\",\"x\":1},{\"frameX\":-16,\"y\":147,\"frameY\":-28,\"frameWidth\":46,\"width\":25,\"frameHeight\":38,\"height\":3,\"name\":\"1/mouth\",\"x\":81},{\"width\":37,\"y\":185,\"height\":23,\"name\":\"1/yanzhao\",\"x\":209},{\"width\":31,\"y\":210,\"height\":21,\"name\":\"1/kouzhao\",\"x\":218},{\"width\":51,\"y\":1,\"height\":36,\"name\":\"1/gangkui\",\"x\":191},{\"frameX\":-4,\"y\":155,\"frameY\":-19,\"frameWidth\":90,\"width\":76,\"frameHeight\":90,\"height\":28,\"name\":\"chen/Smoke 020 Trail Right loop_00001\",\"x\":81},{\"frameX\":-5,\"y\":139,\"frameY\":-17,\"frameWidth\":90,\"width\":78,\"frameHeight\":90,\"height\":30,\"name\":\"chen/Smoke 020 Trail Right loop_00000\",\"x\":1},{\"frameX\":-3,\"y\":171,\"frameY\":-20,\"frameWidth\":90,\"width\":75,\"frameHeight\":90,\"height\":28,\"name\":\"chen/Smoke 020 Trail Right loop_00002\",\"x\":1},{\"frameX\":-2,\"y\":124,\"frameY\":-18,\"frameWidth\":90,\"width\":78,\"frameHeight\":90,\"height\":29,\"name\":\"chen/Smoke 020 Trail Right loop_00004\",\"x\":156},{\"frameX\":-2,\"y\":155,\"frameY\":-19,\"frameWidth\":90,\"width\":75,\"frameHeight\":90,\"height\":28,\"name\":\"chen/Smoke 020 Trail Right loop_00003\",\"x\":159},{\"frameX\":-2,\"y\":107,\"frameY\":-18,\"frameWidth\":90,\"width\":80,\"frameHeight\":90,\"height\":30,\"name\":\"chen/Smoke 020 Trail Right loop_00005\",\"x\":1},{\"width\":28,\"y\":201,\"height\":26,\"name\":\"1/背包\",\"x\":43},{\"frameX\":-1,\"y\":68,\"frameY\":-2,\"frameWidth\":20,\"width\":19,\"frameHeight\":21,\"height\":19,\"name\":\"1/RRRL\",\"x\":233},{\"frameX\":0,\"y\":233,\"frameY\":0,\"frameWidth\":24,\"width\":24,\"frameHeight\":27,\"height\":26,\"name\":\"1/shangyi\",\"x\":218},{\"frameX\":-2,\"y\":39,\"frameY\":-1,\"frameWidth\":18,\"width\":16,\"frameHeight\":27,\"height\":27,\"name\":\"1/LLL\",\"x\":233},{\"frameX\":-17,\"y\":243,\"frameY\":-15,\"frameWidth\":46,\"width\":26,\"frameHeight\":38,\"height\":14,\"name\":\"1/eye4\",\"x\":1},{\"frameX\":-5,\"y\":106,\"frameY\":-3,\"frameWidth\":22,\"width\":11,\"frameHeight\":20,\"height\":14,\"name\":\"1/bizi\",\"x\":244},{\"frameX\":-6,\"y\":246,\"frameY\":-3,\"frameWidth\":25,\"width\":12,\"frameHeight\":11,\"height\":8,\"name\":\"1/mouth4\",\"x\":126}],\"width\":257,\"height\":270,\"texUUid\":{\"__uuid__\":\"fanJddG51IqKKUvxmo+eEL\"}}"]],0,0,[0],[0],[0]]