[1,["4bWxvKRGdAKpWtpnvBkCrZ"],["_texture"],[["dragonBones.DragonBonesAtlasAsset",["_name","_atlasJson"],1]],[[0,0,1,3]],[[0,"zhishengji_tex","{\"imagePath\":\"zhishengji_tex.png\",\"name\":\"zhishengji_tex\",\"SubTexture\":[{\"width\":38,\"y\":391,\"height\":36,\"name\":\"直升机2/图层_394\",\"x\":92},{\"width\":89,\"y\":391,\"height\":60,\"name\":\"直升机2/图层_393\",\"x\":1},{\"width\":388,\"y\":1,\"height\":388,\"name\":\"直升机2/图层_396_拷贝_3\",\"x\":391},{\"width\":101,\"y\":359,\"height\":101,\"name\":\"直升机2/图层_396_拷贝_5\",\"x\":781},{\"width\":238,\"y\":180,\"height\":177,\"name\":\"直升机2/21\",\"x\":781},{\"width\":73,\"y\":453,\"height\":55,\"name\":\"直升机2/图层_395\",\"x\":1},{\"width\":388,\"y\":1,\"height\":388,\"name\":\"图层_396_拷贝_3\",\"x\":1},{\"width\":101,\"y\":359,\"height\":101,\"name\":\"图层_396_拷贝_5\",\"x\":884},{\"width\":238,\"y\":1,\"height\":177,\"name\":\"21\",\"x\":781},{\"width\":73,\"y\":453,\"height\":55,\"name\":\"图层_395\",\"x\":76},{\"width\":68,\"y\":391,\"height\":31,\"name\":\"图层_393\",\"x\":210},{\"width\":85,\"y\":461,\"height\":32,\"name\":\"图层_394\",\"x\":151},{\"width\":60,\"y\":424,\"height\":31,\"name\":\"1\",\"x\":210},{\"width\":57,\"y\":391,\"height\":68,\"name\":\"11\",\"x\":151}],\"width\":1021,\"height\":510,\"texUUid\":{\"__uuid__\":\"4bWxvKRGdAKpWtpnvBkCrZ\"}}"]],0,0,[0],[0],[0]]